kspylib/__init__.py
kspylib/add.py
kspylib-1.0.dist-info/METADATA
kspylib-1.0.dist-info/WHEEL
kspylib-1.0.dist-info/top_level.txt
kspylib-1.0.dist-info/RECORD
